technical_indicators_lib/__init__.py
technical_indicators_lib/indicators.py
technical_indicators_lib-0.0.2.dist-info/LICENSE
technical_indicators_lib-0.0.2.dist-info/METADATA
technical_indicators_lib-0.0.2.dist-info/WHEEL
technical_indicators_lib-0.0.2.dist-info/top_level.txt
technical_indicators_lib-0.0.2.dist-info/RECORD
