Metadata-Version: 2.1
Name: technical_indicators_lib
Version: 0.0.2
Summary: Technical Indicators Library provides means to derive stock market technical indicators.
Home-page: https://github.com/kunalkini015/technical_indicators_lib.git
Author: Kunal Kini K
Author-email: kunalkini15@gmail.com
License: MIT
Platform: UNKNOWN
Classifier: Development Status :: 4 - Beta
Classifier: License :: OSI Approved :: MIT License
Classifier: Programming Language :: Python
Classifier: Programming Language :: Python :: 3.5
Classifier: Programming Language :: Python :: 3.6
Classifier: Programming Language :: Python :: 3.7
Classifier: Programming Language :: Python :: 3.8
Classifier: Programming Language :: Python :: 3.9
Classifier: Topic :: Software Development :: Libraries
Classifier: Topic :: Software Development :: Libraries :: Python Modules
Classifier: Intended Audience :: Developers
Classifier: Intended Audience :: Financial and Insurance Industry
Requires-Python: >=3.5
